data_generation/__init__.py
data_generation/data_generation.py
deep_expts/__init__.py
deep_expts/deep_nn.py
wide_expts/__init__.py
wide_expts/wide_nn.py
mmlpinap-0.0.1.dist-info/LICENSE
mmlpinap-0.0.1.dist-info/METADATA
mmlpinap-0.0.1.dist-info/WHEEL
mmlpinap-0.0.1.dist-info/top_level.txt
mmlpinap-0.0.1.dist-info/RECORD
