Metadata-Version: 2.1
Name: mmlpinap
Version: 0.0.1
Summary: Modern Machine Learning Practices in Asset Pricing
Home-page: https://github.com/akashsonowal/modern-ml-in-asset-pricing
Author: Akash Sonowal
Author-email: akashsonowal.cheme@gmail.com
License: UNKNOWN
Project-URL: Bug Tracker, https://github.com/akashsonowal/modern-ml-in-asset-pricing/issues
Platform: UNKNOWN
Classifier: Programming Language :: Python :: 3
Classifier: License :: OSI Approved :: MIT License
Classifier: Operating System :: OS Independent
Requires-Python: >=3.6
